glotter/__init__.py
glotter/__main__.py
glotter/auto_gen_test.py
glotter/batch.py
glotter/check.py
glotter/containerfactory.py
glotter/decorators.py
glotter/download.py
glotter/errors.py
glotter/project.py
glotter/report.py
glotter/run.py
glotter/settings.py
glotter/singleton.py
glotter/source.py
glotter/test.py
glotter/test_doc_generator.py
glotter/test_generator.py
glotter/testinfo.py
glotter/utils.py
glotter2-0.14.0.dist-info/WHEEL
glotter2-0.14.0.dist-info/entry_points.txt
glotter2-0.14.0.dist-info/METADATA
glotter2-0.14.0.dist-info/RECORD
