Metadata-Version: 2.3
Name: glotter2
Version: 0.14.0
Summary: An execution library for scripts written in any language. This is a fork of https://github.com/auroq/glotter
Author: auroq, rzuckerm
License: LICENSE.txt
Classifier: Development Status :: 5 - Production/Stable
Classifier: License :: OSI Approved :: MIT License
Classifier: Operating System :: OS Independent
Classifier: Programming Language :: Python :: 3
Classifier: Programming Language :: Python :: 3.9
Classifier: Programming Language :: Python :: 3.10
Classifier: Programming Language :: Python :: 3.11
Classifier: Programming Language :: Python :: 3.12
Classifier: Programming Language :: Python :: 3.13
Classifier: Programming Language :: Python :: 3.14
Requires-Dist: docker>=7.1.0,<8.0
Requires-Dist: jinja2>=3.1.2,<4.0
Requires-Dist: pytest>=8.3.5,<9.0
Requires-Dist: pyyaml>6.0,<7.0
Requires-Dist: pytest-xdist>=3.6.1,<4.0
Requires-Dist: pydantic>=2.12,<3
Requires-Dist: pydantic-core>=2.33.2,<3.0.0
Requires-Dist: ruff>=0.14.0,<0.15.0
Requires-Python: >=3.9, <4.0
Project-URL: Bug Tracker, https://github.com/rzuckerm/glotter2/issues
Project-URL: Changelog, https://github.com/rzuckerm/glotter2#changelog
Project-URL: homepage, https://github.com/rzuckerm/glotter2
Project-URL: documentation, https://rzuckerm.github.io/glotter2
